sce/__init__.py
vpolo/__init__.py
vpolo/alevin/__init__.py
vpolo/alevin/parser.py
vpolo/avs_tools/Alevin.py
vpolo/avs_tools/Alevin_MST.py
vpolo/avs_tools/CellRanger.py
vpolo/avs_tools/Dedup.py
vpolo/avs_tools/EM.py
vpolo/avs_tools/EqClass.py
vpolo/avs_tools/Kallisto.py
vpolo/avs_tools/Parsing.py
vpolo/avs_tools/Proof.py
vpolo/avs_tools/Utools.py
vpolo/avs_tools/__init__.py
vpolo-0.3.0.dist-info/LICENSE
vpolo-0.3.0.dist-info/METADATA
vpolo-0.3.0.dist-info/WHEEL
vpolo-0.3.0.dist-info/top_level.txt
vpolo-0.3.0.dist-info/RECORD
