Metadata-Version: 2.1
Name: vpolo
Version: 0.3.0
Summary: Support packages for Alevin tools
Home-page: https://github.com/k3yavi/vpolo
Author: Avi Srivastava
Author-email: asrivastava@cs.stonybrook.edu
License: UNKNOWN
Platform: UNKNOWN
Classifier: Programming Language :: Python :: 3
Classifier: License :: OSI Approved :: MIT License
Classifier: Operating System :: OS Independent
Requires-Dist: pandas
Requires-Dist: scipy
